<annotation>
	                <folder>annots</folder>
	                <filename>00929.jpg</filename>
	                <path>C:/Users/midni/Desktop/School/INNO/Dataset/images/00929.jpg</path>
	                <source>
		                <database>Unknown</database>
	                </source>
	                <size>
		                <width>720</width>
		                <height>1160</height>
		                <depth>3</depth>
	                </size>
	                <segmented>0</segmented>
	                    <object>
		                    <name>plate</name>
		                    <pose>Unspecified</pose>
		                    <truncated>0</truncated>
		                    <difficult>0</difficult>
		                    <bndbox>
			                    <xmin>138</xmin>
			                    <ymin>512</ymin>
			                    <xmax>363</xmax>
			                    <ymax>618</ymax>
		                    </bndbox>
	                    </object>
</annotation>
